regspline/__init__.py
regspline/base.py
regspline/linear_spline.py
regspline/natural_cubic_spline.py
regspline/util.py
regspline-25.7.2.dist-info/licenses/LICENSE
regspline-25.7.2.dist-info/WHEEL
regspline-25.7.2.dist-info/METADATA
regspline-25.7.2.dist-info/RECORD
