Metadata-Version: 2.4
Name: regspline
Version: 25.7.2
Summary: Regression spline
Keywords: statistics,regression,splines
Author: Martin van der Schans
Requires-Python: >=3.9
License-File: LICENSE
Requires-Dist: numpy
Requires-Dist: pandas
Requires-Dist: statsmodels
Requires-Dist: pyqreg ; extra == "fastqr"
Requires-Dist: cvxopt!=1.3.0 ; extra == "lasso"
Requires-Dist: scikit-learn ; extra == "svr"
Project-URL: repository, https://github.com/mvds314/regspline
Provides-Extra: fastqr
Provides-Extra: lasso
Provides-Extra: svr
